{
  "gridWrappers": [
    {
      "wrapperAlias": "header",
      "gridContainers": [
        {
          "containerAlias": "header-logo",
          "gridZones": [
            {
              "zoneAlias": "logo",
              "gridBlocks": [
                {
                  "defaultGridBlock": {
                    "blockType": "type-logo",
                    "inside": {
                      "logoMolecule": {
                        "siteLink": "https://www.amsterdam.nl/vga",
                        "alt": "",
                        "logoTextLine-3": "VGA Verzekeringen",
                        "logoColorLine-3": "black"
                      }
                    }
                  }
                }
              ]
            }
          ]
        },
        {
          "containerAlias": "header-nav",
          "containerModifiers": "breakout-container"
        }
      ]
    },
    {
      "wrapperAlias": "contents",
      "gridContainers": [
        {
          "containerAlias": "main",
          "gridZones": [
            {
              "zoneAlias": "nav",
              "columns": 3,
              "zoneModifiers": "push_9",
              "gridBlocks": [
                {
                  "defaultGridBlock": {
                    "blockType": "nav",
                    "inside": {
                      "content": "Navigatie"
                    }
                  }
                }
              ]
            },
            {
              "zoneAlias": "content",
              "columns": 9,
              "zoneModifiers": "pull_3",
              "gridBlocks": [
                {
                  "defaultGridBlock": {
                    "blockType": "form",
                    "inside": {
                      "content": "Formulier"
                    }
                  }
                }
              ]
            }
          ]
        }
      ]
    },
    {
      "wrapperAlias": "footer",
      "gridContainers": [
        {
          "containerAlias": "footer",
          "containerModifiers": "grid-container container_12 grid-footer bgcolor_darkgrey breakout-container",
          "gridZones": [
            {
              "zoneAlias": "footer",
              "gridBlocks": [
                {
                  "defaultGridBlock": {
                    "blockType": "footer",
                    "inside": {
                      "content": "Footer"
                    }
                  }
                }
              ]
            }
          ]
        },
        {
          "containerAlias": "below-footer",
          "gridZones": [
            {
              "zoneAlias": "below-footer-nav",
              "gridBlocks": [
                {
                  "defaultGridBlock": {
                    "blockType": "type-nav-footer",
                    "inside": {
                      "horizontalListMolecule": {
                        "listItems": [
                          {
                            "listItemLabel": "Colofon"
                          },
                          {
                            "listItemLabel": "Proclaimer"
                          }
                        ]
                      }
                    }
                  }
                }
              ]
            }
          ]
        }
      ]
    }
  ]
}
